MANIFEST.in
README
dev-requirements.txt
setup.py
tox.ini
cubicweb_sherpa/__init__.py
cubicweb_sherpa/__pkginfo__.py
cubicweb_sherpa/schema.py
cubicweb_sherpa/site_cubicweb.py
cubicweb_sherpa/uiprops.py
cubicweb_sherpa.egg-info/PKG-INFO
cubicweb_sherpa.egg-info/SOURCES.txt
cubicweb_sherpa.egg-info/dependency_links.txt
cubicweb_sherpa.egg-info/entry_points.txt
cubicweb_sherpa.egg-info/not-zip-safe
cubicweb_sherpa.egg-info/requires.txt
cubicweb_sherpa.egg-info/top_level.txt
cubicweb_sherpa/data/cubes.sherpa.css
cubicweb_sherpa/data/dictionnaire_SEDA2_final.pdf
cubicweb_sherpa/data/favicon-32x32.png
cubicweb_sherpa/data/fonts/Open_Sans/LICENSE.txt
cubicweb_sherpa/data/fonts/Open_Sans/OpenSans-Bold.ttf
cubicweb_sherpa/data/fonts/Open_Sans/OpenSans-BoldItalic.ttf
cubicweb_sherpa/data/fonts/Open_Sans/OpenSans-CondBold.ttf
cubicweb_sherpa/data/fonts/Open_Sans/OpenSans-CondLight.ttf
cubicweb_sherpa/data/fonts/Open_Sans/OpenSans-CondLightItalic.ttf
cubicweb_sherpa/data/fonts/Open_Sans/OpenSans-ExtraBold.ttf
cubicweb_sherpa/data/fonts/Open_Sans/OpenSans-ExtraBoldItalic.ttf
cubicweb_sherpa/data/fonts/Open_Sans/OpenSans-Italic.ttf
cubicweb_sherpa/data/fonts/Open_Sans/OpenSans-Light.ttf
cubicweb_sherpa/data/fonts/Open_Sans/OpenSans-LightItalic.ttf
cubicweb_sherpa/data/fonts/Open_Sans/OpenSans-Regular.ttf
cubicweb_sherpa/data/fonts/Open_Sans/OpenSans-Semibold.ttf
cubicweb_sherpa/data/fonts/Open_Sans/OpenSans-SemiboldItalic.ttf
cubicweb_sherpa/data/fonts/Open_Sans/readme.txt
cubicweb_sherpa/data/fonts/lovelo/Lovelo-Black.otf
cubicweb_sherpa/data/fonts/lovelo/licence.txt
cubicweb_sherpa/data/images/archive_unit.png
cubicweb_sherpa/data/images/authority_record.png
cubicweb_sherpa/data/images/exemple_bordereau.png
cubicweb_sherpa/data/images/exemple_invalide.png
cubicweb_sherpa/data/images/exemple_profil.png
cubicweb_sherpa/data/images/exemple_valide.png
cubicweb_sherpa/data/images/logo_SHERPA.png
cubicweb_sherpa/data/images/logo_SHERPA_2.png
cubicweb_sherpa/data/images/logo_SIAF.png
cubicweb_sherpa/data/images/seda.png
cubicweb_sherpa/data/images/seda2_datamodel.png
cubicweb_sherpa/data/images/sherpa_bordereau.png
cubicweb_sherpa/data/images/sherpa_cinematique.png
cubicweb_sherpa/data/images/sherpa_general.png
