Metadata-Version: 1.1
Name: cubicweb-sherpa
Version: 0.11.0
Summary: SEDA v2 profile generator
Home-page: http://www.cubicweb.org/project/cubicweb-sherpa
Author: LOGILAB S.A. (Paris, FRANCE)
Author-email: contact@logilab.fr
License: GPL
Platform: UNKNOWN
Classifier: Environment :: Web Environment
Classifier: Framework :: CubicWeb
Classifier: Programming Language :: Python
Classifier: Programming Language :: JavaScript
